opensanctions/__init__.py
opensanctions/cli.py
opensanctions/settings.py
opensanctions/util.py
opensanctions/core/__init__.py
opensanctions/core/addresses.py
opensanctions/core/collection.py
opensanctions/core/context.py
opensanctions/core/dataset.py
opensanctions/core/entity.py
opensanctions/core/http.py
opensanctions/core/index.py
opensanctions/core/loader.py
opensanctions/core/logs.py
opensanctions/core/lookups.py
opensanctions/core/resolver.py
opensanctions/core/source.py
opensanctions/core/xref.py
opensanctions/crawlers/__init__.py
opensanctions/crawlers/adb_sanctions.py
opensanctions/crawlers/afdb_sanctions.py
opensanctions/crawlers/au_dfat_sanctions.py
opensanctions/crawlers/ca_dfatd_sema_sanctions.py
opensanctions/crawlers/ch_seco_sanctions.py
opensanctions/crawlers/coe_assembly.py
opensanctions/crawlers/ebrd_ineligible.py
opensanctions/crawlers/eu_cor_members.py
opensanctions/crawlers/eu_fsf.py
opensanctions/crawlers/eu_meps.py
opensanctions/crawlers/everypolitician.py
opensanctions/crawlers/fr_tresor_gels_avoir.py
opensanctions/crawlers/gb_coh_disqualified.py
opensanctions/crawlers/gb_hmt_sanctions.py
opensanctions/crawlers/iadb_sanctions.py
opensanctions/crawlers/il_mod_terrorists.py
opensanctions/crawlers/interpol_api.py
opensanctions/crawlers/jp_mof_sanctions.py
opensanctions/crawlers/kg_fiu_national.py
opensanctions/crawlers/kz_afmrk_sanctions.py
opensanctions/crawlers/ru_fedsfm_terror.py
opensanctions/crawlers/ru_fedsfm_wmd.py
opensanctions/crawlers/ua_nsdc_sanctions.py
opensanctions/crawlers/ua_sfms_blacklist.py
opensanctions/crawlers/un_ops_vendors.py
opensanctions/crawlers/un_sc_sanctions.py
opensanctions/crawlers/us_bis_denied.py
opensanctions/crawlers/us_cia_world_leaders.py
opensanctions/crawlers/us_ofac.py
opensanctions/crawlers/us_trade_csl.py
opensanctions/crawlers/wd_curated.py
opensanctions/crawlers/wd_peppercat.py
opensanctions/crawlers/worldbank_debarred.py
opensanctions/exporters/__init__.py
opensanctions/exporters/common.py
opensanctions-3.2.0.dist-info/LICENSE
opensanctions-3.2.0.dist-info/METADATA
opensanctions-3.2.0.dist-info/WHEEL
opensanctions-3.2.0.dist-info/entry_points.txt
opensanctions-3.2.0.dist-info/namespace_packages.txt
opensanctions-3.2.0.dist-info/top_level.txt
opensanctions-3.2.0.dist-info/RECORD
